{
  "project_id": "retail-search",
  "project_name": "Retail Search",
  "mde_status": "active",
  "artifact_profiles": [
    "mde_project",
    "mission_driven_engineering"
  ],
  "context_packs": [],
  "validation_strategy_status": "active",
  "latest_generation": "GEN-001",
  "latest_validation_gate_result": "pass_with_external_blockers",
  "upstream_dependencies": [
    "mde"
  ],
  "downstream_dependencies": [],
  "repository_root": "/Users/feroshjacob/code/retail-search",
  "repository_url": "https://github.com/Northvalley-Intelligence/retail-search",
  "public_phase_1_status": "local_foundation_complete_external_deployment_blocked",
  "last_sync_note": "GEN-001 created public GitHub repo and local Cranfield/OpenSearch foundation. Central portfolio registration is still pending from central mde."
}
