{
  "project_id": "retail-search",
  "updated_at": "2026-07-05",
  "findings": [
    {
      "id": "FIND-001",
      "severity": "High",
      "status": "resolved",
      "category": "Deployment",
      "summary": "Public Phase 1 endpoints are deployed and verified against the live cranfield-v0 OpenSearch index."
    },
    {
      "id": "FIND-002",
      "severity": "High",
      "status": "resolved",
      "category": "External Validation",
      "summary": "Full Cranfield export is implemented, cranfield-v0 is loaded with 1,400 live documents, and live evaluation metrics were recorded."
    },
    {
      "id": "FIND-003",
      "severity": "Medium",
      "status": "resolved",
      "category": "Deployment",
      "summary": "Cloudflare Workers write scope was proven by secret upload and Worker deployment."
    }
  ],
  "residual_risks": [
    "Public endpoint p95 latency needs a broader sampled run beyond point checks.",
    "Provider cost depends on the selected managed OpenSearch service plan and usage."
  ]
}
